envsanitycheck/__init__.py
envsanitycheck/cli.py
envsanitycheck-1.0.2.dist-info/METADATA
envsanitycheck-1.0.2.dist-info/WHEEL
envsanitycheck-1.0.2.dist-info/entry_points.txt
envsanitycheck-1.0.2.dist-info/top_level.txt
envsanitycheck-1.0.2.dist-info/RECORD
