Metadata-Version: 2.4
Name: envsanitycheck
Version: 1.0.2
Summary: A robust CLI tool for validating project environment variables (.env files) with type checking.
Home-page: https://github.com/trmxvibs/EnvSanityCheck
Author: Lokesh Kumar
License: MIT
Classifier: Development Status :: 5 - Production/Stable
Classifier: Environment :: Console
Classifier: Intended Audience :: Developers
Classifier: License :: OSI Approved :: MIT License
Classifier: Programming Language :: Python :: 3
Classifier: Programming Language :: Python :: 3.7
Classifier: Programming Language :: Python :: 3.8
Classifier: Programming Language :: Python :: 3.9
Classifier: Programming Language :: Python :: 3.10
Classifier: Programming Language :: Python :: 3.11
Classifier: Topic :: Software Development :: Quality Assurance
Classifier: Topic :: Utilities
Requires-Dist: click
Requires-Dist: ruamel.yaml
Dynamic: author
Dynamic: classifier
Dynamic: description
Dynamic: description-content-type
Dynamic: home-page
Dynamic: license
Dynamic: requires-dist
Dynamic: summary
